<?xml version='1.0' encoding='UTF-8'?>
<song xmlns="http://openlyrics.info/namespace/2009/song" version="0.8" createdIn="OpenLP 3.1.7" modifiedIn="OpenLP 3.1.7" modifiedDate="2026-02-06T14:18:16">
  <properties>
    <titles>
      <title>Kiedy cichnie gwar</title>
    </titles>
    <authors>
      <author>Nieznany</author>
    </authors>
    <themes>
      <theme>worship</theme>
    </themes>
  </properties>
  <lyrics>
    <verse name="v1">
      <lines>Kiedy cichnie gwar, wszystko kończy się, wtedy szukam Cię, chcę Ci przynieść coś, co wartościowe jest, co ucieszy Cię.</lines>
    </verse>
    <verse name="v2">
      <lines>Chcę dać Ci więcej, niż pieśń, <br/>bo wiem, że śpiew nie jest tym, czego ode mnie chcesz.<br/>Ty patrzysz głębiej niż my,<br/>mimo pozorów spraw,<br/>Ty patrzysz w duszę mą.</lines>
    </verse>
    <verse name="v3">
      <lines>ref. Powracam znowu, by wielbić Ciebie, by wywyższać Cię, wywyższać Ciebie wciąż. Przepraszam Ciebie za moje grzechy, chcę wywyższać Cię, wywyższać Ciebie wciąż. dać Ci więcej, niż pieśń, bo wiem, że śpiew nie jest tym, czego ode mnie chcesz. Ty patrzysz głębiej niż my, mimo pozorów spraw, Ty patrzysz w duszę mą.</lines>
    </verse>
  </lyrics>
</song>
